leo_mcp_from_ssh/__init__.py
leo_mcp_from_ssh-0.1.1.dist-info/WHEEL
leo_mcp_from_ssh-0.1.1.dist-info/entry_points.txt
leo_mcp_from_ssh-0.1.1.dist-info/METADATA
leo_mcp_from_ssh-0.1.1.dist-info/RECORD
