Metadata-Version: 2.3
Name: leo-mcp-from-ssh
Version: 0.1.1
Summary: A MCP server deployed at SSH with various utility tools
Requires-Dist: mcp[cli]>=1.12.3
Requires-Python: >=3.12
